ryba/__init__.py
ryba/__main__.py
ryba/cli.py
ryba/config.py
ryba/constants.py
ryba/directories.py
ryba/exceptions.py
ryba/logging.py
ryba/registry.py
ryba/commands/__init__.py
ryba/commands/backup.py
ryba/commands/rotate.py
ryba/commands/snapshot.py
ryba/rotators/__init__.py
ryba/rotators/_base.py
ryba/rotators/_date.py
ryba/rotators/_simple.py
ryba/targets/__init__.py
ryba/targets/_base.py
ryba/targets/_local.py
ryba/targets/_ssh.py
ryba-0.1.1.dist-info/LICENSE
ryba-0.1.1.dist-info/METADATA
ryba-0.1.1.dist-info/WHEEL
ryba-0.1.1.dist-info/entry_points.txt
ryba-0.1.1.dist-info/top_level.txt
ryba-0.1.1.dist-info/RECORD
