Metadata-Version: 2.1
Name: ryba
Version: 0.1.1
Summary: Back up your personal files using rsync
Home-page: https://github.com/timheap/ryba
Author: Tim Heap
Author-email: tim@timheap.me
License: UNKNOWN
Project-URL: Bug Tracker, https://github.com/timheap/ryba/issues
Platform: UNKNOWN
Classifier: Programming Language :: Python :: 3
Classifier: License :: OSI Approved :: BSD License
Classifier: Operating System :: OS Independent
Requires-Python: >=3.9
License-File: LICENSE
Requires-Dist: attrs
Requires-Dist: spur (~=0.3.22)
Requires-Dist: iso8601 (>0.1<0.1.14)
Requires-Dist: toml (~=0.10.2)
Requires-Dist: xdg (~=5.0)
